MANIFEST.in
README.txt
setup.py
c2/__init__.py
c2.splitter.mecabja.egg-info/PKG-INFO
c2.splitter.mecabja.egg-info/SOURCES.txt
c2.splitter.mecabja.egg-info/dependency_links.txt
c2.splitter.mecabja.egg-info/entry_points.txt
c2.splitter.mecabja.egg-info/namespace_packages.txt
c2.splitter.mecabja.egg-info/not-zip-safe
c2.splitter.mecabja.egg-info/requires.txt
c2.splitter.mecabja.egg-info/top_level.txt
c2/splitter/__init__.py
c2/splitter/mecabja/__init__.py
c2/splitter/mecabja/configure.zcml
c2/splitter/mecabja/main.py
c2/splitter/mecabja/tests.py
c2/splitter/mecabja/version.txt
docs/HISTORY.txt
docs/INSTALL.txt
docs/LICENSE.GPL
docs/LICENSE.txt