Metadata-Version: 1.1
Name: c2.splitter.mecabja
Version: 1.0b3
Summary: This product is Japanese splitter by Mecab for Plone
Home-page: http://www.cmscom.jp
Author: Manabu TERADA
Author-email: terada@cmscom.jp
License: GPL
Keywords: plone splitter Japanese  mecab
Platform: UNKNOWN
Classifier: Framework :: Plone
Classifier: Programming Language :: Python
